piate/__init__.py
piate/api/__init__.py
piate/api/client.py
piate/api/credentials.py
piate/api/response.py
piate/api/session.py
piate/api/version.py
piate/api/authentication/__init__.py
piate/api/authentication/v1.py
piate/api/authentication/v2.py
piate/api/resources/__init__.py
piate/api/resources/collections.py
piate/api/resources/domains.py
piate/api/resources/institutions.py
piate/api/resources/inventories.py
piate/cli/__init__.py
piate/cli/format.py
piate/cli/render.py
piate-0.1.6.dist-info/LICENSE
piate-0.1.6.dist-info/METADATA
piate-0.1.6.dist-info/WHEEL
piate-0.1.6.dist-info/entry_points.txt
piate-0.1.6.dist-info/top_level.txt
piate-0.1.6.dist-info/RECORD
