Metadata-Version: 2.1
Name: piate
Version: 0.1.6
Summary: Python Library to interact with the IATE database
Home-page: https://www.github.com/drewsonne/piate
Author: Drew J. Sonne
Author-email: drew.sonne@gmail.com
License: Apache
Platform: UNKNOWN
License-File: LICENSE
Requires-Dist: requests
Requires-Dist: dataclasses-json
Requires-Dist: click
